proteinworkshop/__init__.py
proteinworkshop/config/aux_task/README.md
proteinworkshop/config/aux_task/inverse_folding.yaml
proteinworkshop/config/aux_task/nn_sequence.yaml
proteinworkshop/config/aux_task/nn_structure_r3.yaml
proteinworkshop/config/aux_task/nn_structure_torsion.yaml
proteinworkshop/config/aux_task/none.yaml
proteinworkshop/config/callbacks/default.yaml
proteinworkshop/config/callbacks/early_stopping.yaml
proteinworkshop/config/callbacks/ema.yaml
proteinworkshop/config/callbacks/learning_rate_monitor.yaml
proteinworkshop/config/callbacks/model_checkpoint.yaml
proteinworkshop/config/callbacks/model_summary.yaml
proteinworkshop/config/callbacks/none.yaml
proteinworkshop/config/callbacks/rich_progress_bar.yaml
proteinworkshop/config/callbacks/stop_on_nan.yaml
proteinworkshop/config/dataset/a_thaliana.yaml
proteinworkshop/config/dataset/afdb_rep_dark_v4.yaml
proteinworkshop/config/dataset/afdb_rep_v4.yaml
proteinworkshop/config/dataset/afdb_swissprot_v4.yaml
proteinworkshop/config/dataset/afdb_uniprot_v4.yaml
proteinworkshop/config/dataset/antibody_developability.yaml
proteinworkshop/config/dataset/astral.yaml
proteinworkshop/config/dataset/atom3d_msp.yaml
proteinworkshop/config/dataset/atom3d_ppi.yaml
proteinworkshop/config/dataset/atom3d_psr.yaml
proteinworkshop/config/dataset/atom3d_res.yaml
proteinworkshop/config/dataset/c_albicans.yaml
proteinworkshop/config/dataset/c_elegans.yaml
proteinworkshop/config/dataset/cath.yaml
proteinworkshop/config/dataset/ccpdb_ligands.yaml
proteinworkshop/config/dataset/ccpdb_metal.yaml
proteinworkshop/config/dataset/ccpdb_nucleic.yaml
proteinworkshop/config/dataset/ccpdb_nucleotides.yaml
proteinworkshop/config/dataset/d_discoideum.yaml
proteinworkshop/config/dataset/d_melaogaster.yaml
proteinworkshop/config/dataset/d_rerio.yaml
proteinworkshop/config/dataset/deep_sea_proteins.yaml
proteinworkshop/config/dataset/dummy.yaml
proteinworkshop/config/dataset/e_coli.yaml
proteinworkshop/config/dataset/ec_reaction.yaml
proteinworkshop-0.2.5.dist-info/LICENSE
proteinworkshop-0.2.5.dist-info/METADATA
proteinworkshop-0.2.5.dist-info/WHEEL
proteinworkshop-0.2.5.dist-info/entry_points.txt
proteinworkshop-0.2.5.dist-info/RECORD
