Metadata-Version: 2.1
Name: proteinworkshop
Version: 0.2.5
Summary: 
Home-page: https://www.proteins.sh
License: MIT
Keywords: proteins,deep learning,datasets,benchmarks
Author: Arian Jamasb
Author-email: arian@jamasb.io
Requires-Python: >=3.9,<3.11
Classifier: Intended Audience :: Science/Research
Classifier: License :: OSI Approved :: MIT License
Classifier: Operating System :: OS Independent
Classifier: Programming Language :: Python
Classifier: Programming Language :: Python :: 3
Classifier: Programming Language :: Python :: 3.9
Classifier: Programming Language :: Python :: 3.10
Classifier: Programming Language :: Python :: 3 :: Only
Classifier: Programming Language :: Python :: 3.11
Classifier: Topic :: Scientific/Engineering
Requires-Dist: beartype (>=0.15.0,<0.16.0)
Requires-Dist: biotite (>=0.37.0,<0.38.0)
Requires-Dist: captum (>=0.6.0,<0.7.0)
Requires-Dist: datashader (>=0.16.0,<0.17.0)
Requires-Dist: e3nn (>=0.5.1,<0.6.0)
Requires-Dist: einops (>=0.6.1,<0.7.0)
Requires-Dist: fair-esm (>=2.0.0,<3.0.0)
Requires-Dist: foldcomp (>=0.0.5,<0.0.6)
Requires-Dist: graphein (>=1.7.5,<2.0.0)
Requires-Dist: holoviews (>=1.18.0,<2.0.0)
Requires-Dist: hydra-colorlog (>=1.2.0,<2.0.0)
Requires-Dist: hydra-core (>=1.3.2,<2.0.0)
Requires-Dist: jaxtyping (>=0.2.24,<0.3.0)
Requires-Dist: lightning (>=2.0.7,<3.0.0)
Requires-Dist: loguru (>=0.7.0,<0.8.0)
Requires-Dist: lovely-tensors (>=0.1.15,<0.2.0)
Requires-Dist: matplotlib (>=3.7.2,<4.0.0)
Requires-Dist: omegaconf (>=2.3.0,<3.0.0)
Requires-Dist: opt-einsum (>=3.3.0,<4.0.0)
Requires-Dist: psutil (>=5.9.5,<6.0.0)
Requires-Dist: pyrootutils (>=1.0.4,<2.0.0)
Requires-Dist: pytdc (>=0.4.1,<0.5.0)
Requires-Dist: python-dotenv (>=1.0.0,<2.0.0)
Requires-Dist: pytorch-lightning (>=2.0.7,<3.0.0)
Requires-Dist: rich (>=13.5.2,<14.0.0)
Requires-Dist: torch (>=2.1.2,<3.0.0)
Requires-Dist: torch-geometric (>=2.4.0,<3.0.0)
Requires-Dist: torchmetrics (>=1.2.0,<2.0.0)
Requires-Dist: tqdm (>=4.66.1,<5.0.0)
Requires-Dist: umap-learn (>=0.5.4,<0.6.0)
Requires-Dist: wandb (>=0.15.8,<0.16.0)
Requires-Dist: wget (>=3.2,<4.0)
Project-URL: Bug Tracker, https://github.com/a-r-j/ProteinWorkshop/issues
Project-URL: Documentation, https://proteins.sh
Project-URL: Repository, https://www.github.com/a-r-j/ProteinWorkshop
